hctef/__init__.py
hctef/__version__.py
hctef/exceptions.py
hctef/file_read_cache.py
hctef/http_file.py
hctef/interval_tree.py
hctef/py.typed
hctef/aio/__init__.py
hctef/aio/async_file_read_cache.py
hctef/aio/async_http_file.py
hctef-0.1.1.dist-info/METADATA
hctef-0.1.1.dist-info/WHEEL
hctef-0.1.1.dist-info/RECORD
