Metadata-Version: 2.4
Name: hctef
Version: 0.1.1
Summary: Helper classes to read files over HTTP using Range requests, with caching
Project-URL: Repository, https://github.com/jkeifer/hctef
Author-email: Jarrett Keifer <jkeifer0@gmail.com>
License: Apache License 2.0
Requires-Python: >=3.12
Provides-Extra: async
Requires-Dist: aiohttp>=3.13.0; extra == 'async'
